[
  {
    "tipoRie": "L9",
    "tipoVeh": "CARROCERIA DE METAL",
    "claseVeh": "MOTOCICLETA",
    "numPue": "1",
    "idTipoVeh": 12,
    "keyTipoVeh": "metalicBody",
    "idClaseVeh": 8,
    "keyClaseVeh": "motorcycle",
    "tipoTransmision": null,
    "modelo": {
      "codModelo": "0331407",
      "descModelo": "X PULSE 200 EFI",
      "descModeloStd": null,
      "descCategoriaMtc": null,
      "codModeloAPESEG": "00000010007190"
    }
  },
  {
    "tipoRie": "L6",
    "tipoVeh": "CARROCERIA DE METAL",
    "claseVeh": "MOTOCICLETA",
    "numPue": "2",
    "idTipoVeh": 12,
    "keyTipoVeh": "metalicBody",
    "idClaseVeh": 8,
    "keyClaseVeh": "motorcycle",
    "tipoTransmision": null,
    "modelo": {
      "codModelo": "0331430",
      "descModelo": "XPULSE 200",
      "descModeloStd": "XPULSE 200",
      "descCategoriaMtc": null,
      "codModeloAPESEG": "00000000009714"
    }
  },
  {
    "tipoRie": "L6",
    "tipoVeh": "CARROCERIA DE METAL",
    "claseVeh": "MOTOCICLETA",
    "numPue": "2",
    "idTipoVeh": 12,
    "keyTipoVeh": "metalicBody",
    "idClaseVeh": 8,
    "keyClaseVeh": "motorcycle",
    "tipoTransmision": null,
    "modelo": {
      "codModelo": "0327658",
      "descModelo": "PLEASURE MOTO",
      "descModeloStd": "PLEASURE",
      "descCategoriaMtc": null,
      "codModeloAPESEG": "00000000009714"
    }
  },
  {
    "tipoRie": "LX",
    "tipoVeh": "CARROCERIA DE METAL",
    "claseVeh": "MOTOCICLETA",
    "numPue": "1",
    "idTipoVeh": 12,
    "keyTipoVeh": "metalicBody",
    "idClaseVeh": 8,
    "keyClaseVeh": "motorcycle",
    "tipoTransmision": null,
    "modelo": {
      "codModelo": "0256578",
      "descModelo": "PASSION PRO",
      "descModeloStd": "PASSION PRO",
      "descCategoriaMtc": null,
      "codModeloAPESEG": "00000010001832"
    }
  },
  {
    "tipoRie": "L6",
    "tipoVeh": "CARROCERIA DE METAL",
    "claseVeh": "MOTOCICLETA",
    "numPue": "1",
    "idTipoVeh": 12,
    "keyTipoVeh": "metalicBody",
    "idClaseVeh": 8,
    "keyClaseVeh": "motorcycle",
    "tipoTransmision": null,
    "modelo": {
      "codModelo": "0263693",
      "descModelo": "PLEASURE",
      "descModeloStd": "PLEASURE",
      "descCategoriaMtc": null,
      "codModeloAPESEG": "00000000009714"
    }
  },
  {
    "tipoRie": "L9",
    "tipoVeh": "CARROCERIA DE METAL",
    "claseVeh": "MOTOCICLETA",
    "numPue": "null",
    "idTipoVeh": 12,
    "keyTipoVeh": "metalicBody",
    "idClaseVeh": 8,
    "keyClaseVeh": "motorcycle",
    "tipoTransmision": null,
    "modelo": {
      "codModelo": "0268301",
      "descModelo": "PASSIONPRO/ NG",
      "descModeloStd": "PASSIONPRO/ NG",
      "descCategoriaMtc": null,
      "codModeloAPESEG": "00000010001832"
    }
  },
  {
    "tipoRie": "L6",
    "tipoVeh": "CARROCERIA DE METAL",
    "claseVeh": "MOTOCICLETA",
    "numPue": "2",
    "idTipoVeh": 12,
    "keyTipoVeh": "metalicBody",
    "idClaseVeh": 8,
    "keyClaseVeh": "motorcycle",
    "tipoTransmision": null,
    "modelo": {
      "codModelo": "0332888",
      "descModelo": "S/M",
      "descModeloStd": "S/M",
      "descCategoriaMtc": null,
      "codModeloAPESEG": "00000000009584"
    }
  },
  {
    "tipoRie": "L6",
    "tipoVeh": "CARROCERIA DE METAL",
    "claseVeh": "MOTOCICLETA",
    "numPue": "5",
    "idTipoVeh": 12,
    "keyTipoVeh": "metalicBody",
    "idClaseVeh": 8,
    "keyClaseVeh": "motorcycle",
    "tipoTransmision": null,
    "modelo": {
      "codModelo": "0266576",
      "descModelo": "KARIZMA",
      "descModeloStd": "KARIZMA",
      "descCategoriaMtc": null,
      "codModeloAPESEG": "00000000009714"
    }
  },
  {
    "tipoRie": "L9",
    "tipoVeh": "CARROCERIA DE METAL",
    "claseVeh": "MOTOCICLETA",
    "numPue": "1",
    "idTipoVeh": 12,
    "keyTipoVeh": "metalicBody",
    "idClaseVeh": 8,
    "keyClaseVeh": "motorcycle",
    "tipoTransmision": null,
    "modelo": {
      "codModelo": "0330901",
      "descModelo": "IGNITOR  125",
      "descModeloStd": "IGNITOR ",
      "descCategoriaMtc": null,
      "codModeloAPESEG": "00000010006930"
    }
  },
  {
    "tipoRie": "L6",
    "tipoVeh": "CARROCERIA DE METAL",
    "claseVeh": "MOTOCICLETA",
    "numPue": "2",
    "idTipoVeh": 12,
    "keyTipoVeh": "metalicBody",
    "idClaseVeh": 8,
    "keyClaseVeh": "motorcycle",
    "tipoTransmision": null,
    "modelo": {
      "codModelo": "0333001",
      "descModelo": "DASH 125",
      "descModeloStd": "DASH 125",
      "descCategoriaMtc": null,
      "codModeloAPESEG": "00000000009714"
    }
  },
  {
    "tipoRie": "L6",
    "tipoVeh": "CARROCERIA DE METAL",
    "claseVeh": "MOTOCICLETA",
    "numPue": "2",
    "idTipoVeh": 12,
    "keyTipoVeh": "metalicBody",
    "idClaseVeh": 8,
    "keyClaseVeh": "motorcycle",
    "tipoTransmision": null,
    "modelo": {
      "codModelo": "0329651",
      "descModelo": "IGNITOR 125",
      "descModeloStd": "IGNITOR",
      "descCategoriaMtc": null,
      "codModeloAPESEG": "00000000009714"
    }
  },
  {
    "tipoRie": "L6",
    "tipoVeh": "CARROCERIA DE METAL",
    "claseVeh": "MOTOCICLETA",
    "numPue": "2",
    "idTipoVeh": 12,
    "keyTipoVeh": "metalicBody",
    "idClaseVeh": 8,
    "keyClaseVeh": "motorcycle",
    "tipoTransmision": null,
    "modelo": {
      "codModelo": "0326502",
      "descModelo": "KARIZMA ZMR",
      "descModeloStd": "KARIZMA",
      "descCategoriaMtc": null,
      "codModeloAPESEG": "00000000009714"
    }
  },
  {
    "tipoRie": "L9",
    "tipoVeh": "CARROCERIA DE METAL",
    "claseVeh": "MOTOCICLETA",
    "numPue": "2",
    "idTipoVeh": 12,
    "keyTipoVeh": "metalicBody",
    "idClaseVeh": 8,
    "keyClaseVeh": "motorcycle",
    "tipoTransmision": null,
    "modelo": {
      "codModelo": "0333190",
      "descModelo": "DASH 125",
      "descModeloStd": "DASH 125",
      "descCategoriaMtc": null,
      "codModeloAPESEG": "00000010008181"
    }
  },
  {
    "tipoRie": "L6",
    "tipoVeh": "CARROCERIA DE METAL",
    "claseVeh": "MOTOCICLETA",
    "numPue": "2",
    "idTipoVeh": 12,
    "keyTipoVeh": "metalicBody",
    "idClaseVeh": 8,
    "keyClaseVeh": "motorcycle",
    "tipoTransmision": null,
    "modelo": {
      "codModelo": "0332932",
      "descModelo": "ECO 150TR",
      "descModeloStd": "ECO 150TR",
      "descCategoriaMtc": null,
      "codModeloAPESEG": "00000000009714"
    }
  },
  {
    "tipoRie": "L6",
    "tipoVeh": "CARROCERIA DE METAL",
    "claseVeh": "MOTOCICLETA",
    "numPue": "2",
    "idTipoVeh": 12,
    "keyTipoVeh": "metalicBody",
    "idClaseVeh": 8,
    "keyClaseVeh": "motorcycle",
    "tipoTransmision": null,
    "modelo": {
      "codModelo": "0331717",
      "descModelo": "PUCH MOTO",
      "descModeloStd": "PUCH",
      "descCategoriaMtc": null,
      "codModeloAPESEG": "00000000009714"
    }
  },
  {
    "tipoRie": "L6",
    "tipoVeh": "CARROCERIA DE METAL",
    "claseVeh": "MOTOCICLETA",
    "numPue": "2",
    "idTipoVeh": 12,
    "keyTipoVeh": "metalicBody",
    "idClaseVeh": 8,
    "keyClaseVeh": "motorcycle",
    "tipoTransmision": null,
    "modelo": {
      "codModelo": "0326503",
      "descModelo": "SPLENDOR I-SIN MODELOART",
      "descModeloStd": "SPLENDOR",
      "descCategoriaMtc": null,
      "codModeloAPESEG": "00000000009714"
    }
  },
  {
    "tipoRie": "L6",
    "tipoVeh": "CARROCERIA DE METAL",
    "claseVeh": "MOTOCICLETA",
    "numPue": "null",
    "idTipoVeh": 12,
    "keyTipoVeh": "metalicBody",
    "idClaseVeh": 8,
    "keyClaseVeh": "motorcycle",
    "tipoTransmision": null,
    "modelo": {
      "codModelo": "0273247",
      "descModelo": "SPLENDOR",
      "descModeloStd": "SPLENDOR",
      "descCategoriaMtc": null,
      "codModeloAPESEG": "00000000009714"
    }
  },
  {
    "tipoRie": "L9",
    "tipoVeh": "CARROCERIA DE METAL",
    "claseVeh": "MOTOCICLETA",
    "numPue": "1",
    "idTipoVeh": 12,
    "keyTipoVeh": "metalicBody",
    "idClaseVeh": 8,
    "keyClaseVeh": "motorcycle",
    "tipoTransmision": null,
    "modelo": {
      "codModelo": "0256605",
      "descModelo": "HUNK",
      "descModeloStd": "HUNK",
      "descCategoriaMtc": null,
      "codModeloAPESEG": "00000000009584"
    }
  },
  {
    "tipoRie": "L6",
    "tipoVeh": "CARROCERIA DE METAL",
    "claseVeh": "MOTOCICLETA",
    "numPue": "2",
    "idTipoVeh": 12,
    "keyTipoVeh": "metalicBody",
    "idClaseVeh": 8,
    "keyClaseVeh": "motorcycle",
    "tipoTransmision": null,
    "modelo": {
      "codModelo": "0334806",
      "descModelo": "HUNK MOTO",
      "descModeloStd": "HUNK",
      "descCategoriaMtc": null,
      "codModeloAPESEG": "00000000009714"
    }
  },
  {
    "tipoRie": "L6",
    "tipoVeh": "CARROCERIA DE METAL",
    "claseVeh": "MOTOCICLETA",
    "numPue": "5",
    "idTipoVeh": 12,
    "keyTipoVeh": "metalicBody",
    "idClaseVeh": 8,
    "keyClaseVeh": "motorcycle",
    "tipoTransmision": null,
    "modelo": {
      "codModelo": "0235635",
      "descModelo": "GLAMOUR",
      "descModeloStd": "GLAMOUR",
      "descCategoriaMtc": null,
      "codModeloAPESEG": "00000000009714"
    }
  },
  {
    "tipoRie": "L6",
    "tipoVeh": "CARROCERIA DE METAL",
    "claseVeh": "MOTOCICLETA",
    "numPue": "null",
    "idTipoVeh": 12,
    "keyTipoVeh": "metalicBody",
    "idClaseVeh": 8,
    "keyClaseVeh": "motorcycle",
    "tipoTransmision": null,
    "modelo": {
      "codModelo": "0274024",
      "descModelo": "THRILLER",
      "descModeloStd": "THRILLER",
      "descCategoriaMtc": null,
      "codModeloAPESEG": "00000000009714"
    }
  },
  {
    "tipoRie": "L9",
    "tipoVeh": "CARROCERIA DE METAL",
    "claseVeh": "MOTOCICLETA",
    "numPue": "2",
    "idTipoVeh": 12,
    "keyTipoVeh": "metalicBody",
    "idClaseVeh": 8,
    "keyClaseVeh": "motorcycle",
    "tipoTransmision": null,
    "modelo": {
      "codModelo": "0331505",
      "descModelo": "DAWN 150",
      "descModeloStd": null,
      "descCategoriaMtc": null,
      "codModeloAPESEG": "00000010007243"
    }
  }
]