[
  {
    "tipoRie": "L6",
    "tipoVeh": "CARROCERIA DE METAL",
    "claseVeh": "MOTOCICLETA",
    "numPue": "2",
    "idTipoVeh": 12,
    "keyTipoVeh": "metalicBody",
    "idClaseVeh": 8,
    "keyClaseVeh": "motorcycle",
    "tipoTransmision": null,
    "modelo": {
      "codModelo": "0332180",
      "descModelo": "WR 150-1",
      "descModeloStd": "WR",
      "descCategoriaMtc": null,
      "codModeloAPESEG": "00000010007612"
    }
  },
  {
    "tipoRie": "L6",
    "tipoVeh": "CARROCERIA DE METAL",
    "claseVeh": "MOTOCICLETA",
    "numPue": "2",
    "idTipoVeh": 12,
    "keyTipoVeh": "metalicBody",
    "idClaseVeh": 8,
    "keyClaseVeh": "motorcycle",
    "tipoTransmision": null,
    "modelo": {
      "codModelo": "0333678",
      "descModelo": "JA 125",
      "descModeloStd": "JA 125",
      "descCategoriaMtc": null,
      "codModeloAPESEG": "00000010007612"
    }
  }
]