[
  {
    "tipoRie": "L6",
    "tipoVeh": "CARROCERIA DE METAL",
    "claseVeh": "MOTOCICLETA",
    "numPue": "null",
    "idTipoVeh": 12,
    "keyTipoVeh": "metalicBody",
    "idClaseVeh": 8,
    "keyClaseVeh": "motorcycle",
    "tipoTransmision": null,
    "modelo": {
      "codModelo": "0315036",
      "descModelo": "ESPECIAL 110",
      "descModeloStd": "ESPECIAL",
      "descCategoriaMtc": null,
      "codModeloAPESEG": "00000010006154"
    }
  },
  {
    "tipoRie": "L6",
    "tipoVeh": "CARROCERIA DE METAL",
    "claseVeh": "MOTOCICLETA",
    "numPue": "null",
    "idTipoVeh": 12,
    "keyTipoVeh": "metalicBody",
    "idClaseVeh": 8,
    "keyClaseVeh": "motorcycle",
    "tipoTransmision": null,
    "modelo": {
      "codModelo": "0283920",
      "descModelo": "WX 150-9",
      "descModeloStd": "WX",
      "descCategoriaMtc": null,
      "codModeloAPESEG": "00000010006154"
    }
  },
  {
    "tipoRie": "L6",
    "tipoVeh": "CARROCERIA DE METAL",
    "claseVeh": "MOTOCICLETA",
    "numPue": "null",
    "idTipoVeh": 12,
    "keyTipoVeh": "metalicBody",
    "idClaseVeh": 8,
    "keyClaseVeh": "motorcycle",
    "tipoTransmision": null,
    "modelo": {
      "codModelo": "0327988",
      "descModelo": "WX200-B",
      "descModeloStd": "WX",
      "descCategoriaMtc": null,
      "codModeloAPESEG": "00000010006154"
    }
  },
  {
    "tipoRie": "L6",
    "tipoVeh": "CARROCERIA DE METAL",
    "claseVeh": "TRIMOTO CARGA",
    "numPue": "null",
    "idTipoVeh": 12,
    "keyTipoVeh": "metalicBody",
    "idClaseVeh": 77,
    "keyClaseVeh": "trimotoCargo",
    "tipoTransmision": null,
    "modelo": {
      "codModelo": "0328735",
      "descModelo": "WX TRI CARGA",
      "descModeloStd": "WX TRI CARGA",
      "descCategoriaMtc": null,
      "codModeloAPESEG": "00000010006154"
    }
  }
]