[
  {
    "tipoRie": "L6",
    "tipoVeh": "CARROCERIA DE METAL",
    "claseVeh": "MOTOCICLETA",
    "numPue": "null",
    "idTipoVeh": 12,
    "keyTipoVeh": "metalicBody",
    "idClaseVeh": 8,
    "keyClaseVeh": "motorcycle",
    "tipoTransmision": null,
    "modelo": {
      "codModelo": "0327024",
      "descModelo": "RTM 200 WOLF",
      "descModeloStd": "RTM 200 WOLF",
      "descCategoriaMtc": null,
      "codModeloAPESEG": "00000000009959"
    }
  },
  {
    "tipoRie": "L6",
    "tipoVeh": "CARROCERIA DE METAL",
    "claseVeh": "MOTOCICLETA",
    "numPue": "1",
    "idTipoVeh": 12,
    "keyTipoVeh": "metalicBody",
    "idClaseVeh": 8,
    "keyClaseVeh": "motorcycle",
    "tipoTransmision": null,
    "modelo": {
      "codModelo": "0169050",
      "descModelo": "YG125 1X",
      "descModeloStd": "YG125-3F",
      "descCategoriaMtc": null,
      "codModeloAPESEG": "00000000009959"
    }
  },
  {
    "tipoRie": "L9",
    "tipoVeh": "CARROCERIA DE METAL",
    "claseVeh": "MOTOCICLETA",
    "numPue": "1",
    "idTipoVeh": 12,
    "keyTipoVeh": "metalicBody",
    "idClaseVeh": 8,
    "keyClaseVeh": "motorcycle",
    "tipoTransmision": null,
    "modelo": {
      "codModelo": "0221973",
      "descModelo": "YG100-5F",
      "descModeloStd": "YG100",
      "descCategoriaMtc": null,
      "codModeloAPESEG": "00000000009959"
    }
  },
  {
    "tipoRie": "L9",
    "tipoVeh": "CARROCERIA DE METAL",
    "claseVeh": "MOTOCICLETA",
    "numPue": "1",
    "idTipoVeh": 12,
    "keyTipoVeh": "metalicBody",
    "idClaseVeh": 8,
    "keyClaseVeh": "motorcycle",
    "tipoTransmision": null,
    "modelo": {
      "codModelo": "0221600",
      "descModelo": "CGL150",
      "descModeloStd": "CGL",
      "descCategoriaMtc": null,
      "codModeloAPESEG": "00000010003831"
    }
  },
  {
    "tipoRie": "L6",
    "tipoVeh": "CARROCERIA DE METAL",
    "claseVeh": "MOTOCICLETA",
    "numPue": "null",
    "idTipoVeh": 12,
    "keyTipoVeh": "metalicBody",
    "idClaseVeh": 8,
    "keyClaseVeh": "motorcycle",
    "tipoTransmision": null,
    "modelo": {
      "codModelo": "0272234",
      "descModelo": "RTM1106",
      "descModeloStd": "RTM1106",
      "descCategoriaMtc": null,
      "codModeloAPESEG": "00000000009959"
    }
  },
  {
    "tipoRie": "L9",
    "tipoVeh": "CARROCERIA DE METAL",
    "claseVeh": "MOTOCICLETA",
    "numPue": "2",
    "idTipoVeh": 12,
    "keyTipoVeh": "metalicBody",
    "idClaseVeh": 8,
    "keyClaseVeh": "motorcycle",
    "tipoTransmision": null,
    "modelo": {
      "codModelo": "0262091",
      "descModelo": "VERO",
      "descModeloStd": "VERO",
      "descCategoriaMtc": null,
      "codModeloAPESEG": "00000010003515"
    }
  },
  {
    "tipoRie": "L6",
    "tipoVeh": "CARROCERIA DE METAL",
    "claseVeh": "TRIMOTO CARGA",
    "numPue": "null",
    "idTipoVeh": 12,
    "keyTipoVeh": "metalicBody",
    "idClaseVeh": 77,
    "keyClaseVeh": "trimotoCargo",
    "tipoTransmision": null,
    "modelo": {
      "codModelo": "0284705",
      "descModelo": "WORLD TRI CARGA",
      "descModeloStd": "WORLD TRI CARGA",
      "descCategoriaMtc": null,
      "codModeloAPESEG": "00000000009959"
    }
  },
  {
    "tipoRie": "L6",
    "tipoVeh": "CARROCERIA DE METAL",
    "claseVeh": "MOTOCICLETA",
    "numPue": "null",
    "idTipoVeh": 12,
    "keyTipoVeh": "metalicBody",
    "idClaseVeh": 8,
    "keyClaseVeh": "motorcycle",
    "tipoTransmision": null,
    "modelo": {
      "codModelo": "0272195",
      "descModelo": "YG150GL",
      "descModeloStd": "YG150GL",
      "descCategoriaMtc": null,
      "codModeloAPESEG": "00000000009959"
    }
  },
  {
    "tipoRie": "L6",
    "tipoVeh": "CARROCERIA DE METAL",
    "claseVeh": "MOTOCICLETA",
    "numPue": "null",
    "idTipoVeh": 12,
    "keyTipoVeh": "metalicBody",
    "idClaseVeh": 8,
    "keyClaseVeh": "motorcycle",
    "tipoTransmision": null,
    "modelo": {
      "codModelo": "0272205",
      "descModelo": "RTM125R2",
      "descModeloStd": "RTM125R2",
      "descCategoriaMtc": null,
      "codModeloAPESEG": "00000000009959"
    }
  },
  {
    "tipoRie": "L6",
    "tipoVeh": "CARROCERIA DE METAL",
    "claseVeh": "MOTOCICLETA",
    "numPue": "null",
    "idTipoVeh": 12,
    "keyTipoVeh": "metalicBody",
    "idClaseVeh": 8,
    "keyClaseVeh": "motorcycle",
    "tipoTransmision": null,
    "modelo": {
      "codModelo": "0327215",
      "descModelo": "YG200GY-A MOTO",
      "descModeloStd": "YG200GY-A",
      "descCategoriaMtc": null,
      "codModeloAPESEG": "00000000009959"
    }
  },
  {
    "tipoRie": "L6",
    "tipoVeh": "CARROCERIA DE METAL",
    "claseVeh": "MOTOCICLETA",
    "numPue": "null",
    "idTipoVeh": 12,
    "keyTipoVeh": "metalicBody",
    "idClaseVeh": 8,
    "keyClaseVeh": "motorcycle",
    "tipoTransmision": null,
    "modelo": {
      "codModelo": "0271107",
      "descModelo": "YG250-4",
      "descModeloStd": "YG250",
      "descCategoriaMtc": null,
      "codModeloAPESEG": "00000000009959"
    }
  },
  {
    "tipoRie": "L6",
    "tipoVeh": "CARROCERIA DE METAL",
    "claseVeh": "MOTOCICLETA",
    "numPue": "null",
    "idTipoVeh": 12,
    "keyTipoVeh": "metalicBody",
    "idClaseVeh": 8,
    "keyClaseVeh": "motorcycle",
    "tipoTransmision": null,
    "modelo": {
      "codModelo": "0323753",
      "descModelo": "TRAIL200",
      "descModeloStd": "TRAIL200",
      "descCategoriaMtc": null,
      "codModeloAPESEG": "00000000009959"
    }
  },
  {
    "tipoRie": "L6",
    "tipoVeh": "CARROCERIA DE METAL",
    "claseVeh": "TRIMOTO PASAJEROS",
    "numPue": "3",
    "idTipoVeh": 12,
    "keyTipoVeh": "metalicBody",
    "idClaseVeh": 78,
    "keyClaseVeh": "trimotoPassenger",
    "tipoTransmision": null,
    "modelo": {
      "codModelo": "0332205",
      "descModelo": "YG 150 GL",
      "descModeloStd": "YG",
      "descCategoriaMtc": null,
      "codModeloAPESEG": "00000000009959"
    }
  },
  {
    "tipoRie": "L6",
    "tipoVeh": "CARROCERIA DE METAL",
    "claseVeh": "MOTOCICLETA",
    "numPue": "2",
    "idTipoVeh": 12,
    "keyTipoVeh": "metalicBody",
    "idClaseVeh": 8,
    "keyClaseVeh": "motorcycle",
    "tipoTransmision": null,
    "modelo": {
      "codModelo": "0263069",
      "descModelo": "TRAIL150",
      "descModeloStd": "TRAIL150",
      "descCategoriaMtc": null,
      "codModeloAPESEG": "00000000009959"
    }
  },
  {
    "tipoRie": "L6",
    "tipoVeh": "CARROCERIA DE METAL",
    "claseVeh": "MOTOCICLETA",
    "numPue": "1",
    "idTipoVeh": 12,
    "keyTipoVeh": "metalicBody",
    "idClaseVeh": 8,
    "keyClaseVeh": "motorcycle",
    "tipoTransmision": null,
    "modelo": {
      "codModelo": "0168609",
      "descModelo": "YG125-3F",
      "descModeloStd": "YG125-3F",
      "descCategoriaMtc": null,
      "codModeloAPESEG": "00000000009959"
    }
  },
  {
    "tipoRie": "L6",
    "tipoVeh": "CARROCERIA DE METAL",
    "claseVeh": "MOTOCICLETA",
    "numPue": "2",
    "idTipoVeh": 12,
    "keyTipoVeh": "metalicBody",
    "idClaseVeh": 8,
    "keyClaseVeh": "motorcycle",
    "tipoTransmision": null,
    "modelo": {
      "codModelo": "0326458",
      "descModelo": "YG200-XL",
      "descModeloStd": "YG200",
      "descCategoriaMtc": null,
      "codModeloAPESEG": "00000000009959"
    }
  }
]